k8s_mcp_server/__init__.py
k8s_mcp_server/k8s_client.py
k8s_mcp_server/server.py
mareana_k8s_mcp_server-0.1.1.dist-info/METADATA
mareana_k8s_mcp_server-0.1.1.dist-info/WHEEL
mareana_k8s_mcp_server-0.1.1.dist-info/entry_points.txt
mareana_k8s_mcp_server-0.1.1.dist-info/RECORD
