Metadata-Version: 2.4
Name: mareana-k8s-mcp-server
Version: 0.1.1
Summary: Kubernetes MCP Server for pod management and monitoring via Dashboard API
Project-URL: Homepage, https://github.com/mareana/k8s-mcp-server
Project-URL: Repository, https://github.com/mareana/k8s-mcp-server
Project-URL: Documentation, https://github.com/mareana/k8s-mcp-server/blob/main/README.md
Project-URL: Issues, https://github.com/mareana/k8s-mcp-server/issues
Author-email: Shashanka G <shashanka.g@mareana.com>
License: MIT
Keywords: dashboard,devops,k8s,kubernetes,mcp,monitoring,pod
Classifier: Development Status :: 4 - Beta
Classifier: Intended Audience :: Developers
Classifier: License :: OSI Approved :: MIT License
Classifier: Programming Language :: Python :: 3
Classifier: Programming Language :: Python :: 3.10
Classifier: Programming Language :: Python :: 3.11
Classifier: Programming Language :: Python :: 3.12
Classifier: Programming Language :: Python :: 3.13
Classifier: Topic :: Software Development :: Libraries :: Python Modules
Classifier: Topic :: System :: Monitoring
Classifier: Topic :: System :: Systems Administration
Requires-Python: >=3.10
Requires-Dist: mcp>=1.0.0
Requires-Dist: requests>=2.31.0
Provides-Extra: dev
Requires-Dist: black>=23.0.0; extra == 'dev'
Requires-Dist: build>=0.10.0; extra == 'dev'
Requires-Dist: mypy>=1.0.0; extra == 'dev'
Requires-Dist: pytest>=7.0.0; extra == 'dev'
Requires-Dist: twine>=4.0.0; extra == 'dev'
